hello/__init__.py
hello/blueprints.txt
hello/entry.py
hello/templates/hello/hello.html
auto_blueprints_hello-0.1.2.dist-info/LICENSE.txt
auto_blueprints_hello-0.1.2.dist-info/METADATA
auto_blueprints_hello-0.1.2.dist-info/WHEEL
auto_blueprints_hello-0.1.2.dist-info/top_level.txt
auto_blueprints_hello-0.1.2.dist-info/RECORD
