Metadata-Version: 2.1
Name: auto-blueprints-hello
Version: 0.1.2
Summary: Flask blueprints auto discovery example
Author-email: David <c0d3@gpobox.net>
Maintainer-email: David <c0d3@gpobox.net>
License: Copyright © 2024 David <c0d3@gpobox.net>
Project-URL: Homepage, https://github.com/bbc6502/blueprints-hello
Project-URL: Bug Tracker, https://github.com/bbc6502/blueprints-hello/issues
Keywords: flask,blueprints
Classifier: Programming Language :: Python :: 3
Classifier: License :: OSI Approved :: MIT License
Classifier: Operating System :: OS Independent
Classifier: Development Status :: 4 - Beta
Requires-Python: >=3.11
License-File: LICENSE.txt
Requires-Dist: auto-blueprints
